luciferase/__init__.py
luciferase/luciferase.py
luciferase/ratioplot.py
luciferase/ratiotest.py
luciferase/swarmplot.py
luciferase/write_table.py
luciferase-2.4.5.dist-info/LICENSE
luciferase-2.4.5.dist-info/METADATA
luciferase-2.4.5.dist-info/WHEEL
luciferase-2.4.5.dist-info/entry_points.txt
luciferase-2.4.5.dist-info/top_level.txt
luciferase-2.4.5.dist-info/RECORD
