Metadata-Version: 2.1
Name: luciferase
Version: 2.4.5
Summary: Helper functions for luciferase data
Home-page: https://gitlab.com/aaylward/luciferase
Author: Anthony Aylward, Joshua Chiou, Mei-Lin Okino
Author-email: aaylward@salk.edu
License: UNKNOWN
Platform: UNKNOWN
Classifier: Programming Language :: Python :: 3
Classifier: License :: OSI Approved :: MIT License
Classifier: Operating System :: OS Independent
License-File: LICENSE
Requires-Dist: estimateratio
Requires-Dist: matplotlib
Requires-Dist: pandas
Requires-Dist: scipy
Requires-Dist: seaborn
Requires-Dist: xlrd
